dx_profiler/cli.py
inference/file_writer.py
inference/inference.py
inference/nats_listener.py
player/controller.py
player/model.py
player/mvc.py
player/view.py
proto_py/dx_pb2.py
proto_py/dx_pb2.pyi
proto_py/dx_pb2_grpc.py
dx_profiler-0.1.3.dist-info/METADATA
dx_profiler-0.1.3.dist-info/WHEEL
dx_profiler-0.1.3.dist-info/entry_points.txt
dx_profiler-0.1.3.dist-info/RECORD
