Metadata-Version: 2.1
Name: dx-profiler
Version: 0.1.3
Summary: Profile Dx App
Author: SangHyeukYoon
Author-email: shyoon@snuailab.ai
Requires-Python: >=3.10,<4.0
Classifier: Programming Language :: Python :: 3
Classifier: Programming Language :: Python :: 3.10
Classifier: Programming Language :: Python :: 3.11
Requires-Dist: grpcio (>=1.56.2,<2.0.0)
Requires-Dist: grpcio-tools (>=1.56.2,<2.0.0)
Requires-Dist: nats-py (>=2.3.1,<3.0.0)
Requires-Dist: opencv-python-headless (>=4.8.0.74,<5.0.0.0)
Requires-Dist: pyqt5 (>=5.15.9,<6.0.0)
Requires-Dist: tqdm (>=4.65.2,<5.0.0)
Requires-Dist: typer[all] (>=0.9.0,<0.10.0)
